dpface/__init__.py
dpface/app/__init__.py
dpface/app/common.py
dpface/app/face_analysis.py
dpface/commands/__init__.py
dpface/commands/model_download.py
dpface/data/__init__.py
dpface/data/pickle_object.py
dpface/data/objects/emap.npy
dpface/data/objects/meanshape_68.pkl
dpface/model_zoo/__init__.py
dpface/model_zoo/arcface_onnx.py
dpface/model_zoo/attribute.py
dpface/model_zoo/inswapper.py
dpface/model_zoo/landmark.py
dpface/model_zoo/model_store.py
dpface/model_zoo/model_zoo.py
dpface/model_zoo/retinaface.py
dpface/utils/__init__.py
dpface/utils/constant.py
dpface/utils/download.py
dpface/utils/face_align.py
dpface/utils/filesystem.py
dpface/utils/storage.py
dpface/utils/transform.py
dpface-0.0.1.dev4.data/data/dpface/data/objects/emap.npy
dpface-0.0.1.dev4.data/data/dpface/data/objects/meanshape_68.pkl
dpface-0.0.1.dev4.dist-info/METADATA
dpface-0.0.1.dev4.dist-info/WHEEL
dpface-0.0.1.dev4.dist-info/top_level.txt
dpface-0.0.1.dev4.dist-info/zip-safe
dpface-0.0.1.dev4.dist-info/RECORD
