Metadata-Version: 2.1
Name: dpface
Version: 0.0.1.dev4
Summary: DeskPai Face Python Library
Home-page: https://github.com/deskpai
Author: Deskpai
Author-email: dev@deskpai.com
License: MIT
